lnhub_rest/__init__.py
lnhub_rest/__main__.py
lnhub_rest/_ci.py
lnhub_rest/_clean_ci.py
lnhub_rest/config.py
lnhub_rest/main.py
lnhub_rest/core/__init__.py
lnhub_rest/core/account/__init__.py
lnhub_rest/core/account/_create_account.py
lnhub_rest/core/account/_crud.py
lnhub_rest/core/account/_delete_account.py
lnhub_rest/core/account/_update_account.py
lnhub_rest/core/collaborator/__init__.py
lnhub_rest/core/collaborator/_crud.py
lnhub_rest/core/db_user/__init__.py
lnhub_rest/core/db_user/_crud.py
lnhub_rest/core/instance/__init__.py
lnhub_rest/core/instance/_crud.py
lnhub_rest/core/instance/_delete_instance.py
lnhub_rest/core/instance/_update_instance.py
lnhub_rest/core/member/__init__.py
lnhub_rest/core/member/_crud.py
lnhub_rest/core/storage/__init__.py
lnhub_rest/core/storage/_crud.py
lnhub_rest/orm/__init__.py
lnhub_rest/orm/_engine.py
lnhub_rest/orm/_sbclient.py
lnhub_rest/routers/__init__.py
lnhub_rest/routers/account.py
lnhub_rest/routers/ci.py
lnhub_rest/routers/cloud_run.py
lnhub_rest/routers/collaborator.py
lnhub_rest/routers/dev.py
lnhub_rest/routers/instance.py
lnhub_rest/routers/organization.py
lnhub_rest/routers/utils.py
lnhub_rest/schema/__init__.py
lnhub_rest/schema/_core.py
lnhub_rest/schema/_timestamps.py
lnhub_rest/schema/_type.py
lnhub_rest/schema/_users.py
lnhub_rest/schema/_versions.py
lnhub_rest/schema/alembic.ini
lnhub_rest/schema/versions.py
lnhub_rest/schema/migrations/__init__.py
lnhub_rest/schema/migrations/clone.py
lnhub_rest/schema/migrations/env.py
lnhub_rest/schema/migrations/script.py.mako
lnhub_rest/schema/migrations/testing.py
lnhub_rest/schema/migrations/function/_2023_02_21_a88f5298b8f7_v0_4_2.py
lnhub_rest/schema/migrations/function/_2023_04_04_6e7d7a97c233_v0_8_dev2.py
lnhub_rest/schema/migrations/function/_2023_04_04_6e7d7a97c233_v0_8_dev3.py
lnhub_rest/schema/migrations/function/_2023_07_21_17dd170649b6_v0_10_2.py
lnhub_rest/schema/migrations/function/__init__.py
lnhub_rest-0.10.18.dist-info/entry_points.txt
lnhub_rest-0.10.18.dist-info/WHEEL
lnhub_rest-0.10.18.dist-info/METADATA
lnhub_rest-0.10.18.dist-info/RECORD
