Metadata-Version: 2.1
Name: lnhub_rest
Version: 0.10.18
Summary: Rest API for the hub.
Author-email: Lamin Labs <laminlabs@gmail.com>
Requires-Dist: lamin_logger
Requires-Dist: supabase==1.0.3
Requires-Dist: pyjwt
Requires-Dist: pydantic[dotenv]
Requires-Dist: pre-commit ; extra == "dev"
Requires-Dist: nox ; extra == "dev"
Requires-Dist: fastapi ; extra == "server"
Requires-Dist: uvicorn ; extra == "server"
Requires-Dist: sqlmodel ; extra == "server"
Requires-Dist: alembic ; extra == "server"
Requires-Dist: pytest_alembic==0.9.1 ; extra == "server"
Requires-Dist: psycopg2-binary ; extra == "server"
Requires-Dist: faker ; extra == "test"
Requires-Dist: pytest>=6.0 ; extra == "test"
Requires-Dist: pytest-cov ; extra == "test"
Requires-Dist: nbproject-test ; extra == "test"
Requires-Dist: botocore ; extra == "test"
Requires-Dist: lamindb_setup ; extra == "test"
Requires-Dist: deepdiff ; extra == "test"
Requires-Dist: pytest-xdist ; extra == "test"
Project-URL: Home, https://github.com/laminlabs/lnhub-rest
Provides-Extra: dev
Provides-Extra: server
Provides-Extra: test
